pssr/__init__.py
pssr/__main__.py
pssr/crappifiers.py
pssr/data.py
pssr/models/__init__.py
pssr/models/_blocks.py
pssr/models/_rdnet.py
pssr/models/rdresunet.py
pssr/models/resunet.py
pssr/models/swinir.py
pssr/napari/__init__.py
pssr/napari/_util.py
pssr/napari/napari.yaml
pssr/napari/widgets.py
pssr/predict.py
pssr/train.py
pssr/util.py
pssr-2.4.0.dist-info/LICENSE
pssr-2.4.0.dist-info/METADATA
pssr-2.4.0.dist-info/NOTICE
pssr-2.4.0.dist-info/WHEEL
pssr-2.4.0.dist-info/entry_points.txt
pssr-2.4.0.dist-info/RECORD
