Metadata-Version: 2.3
Name: pssr
Version: 2.4.0
Summary: Point-Scanning Super-Resolution 2
License: MIT
Author: Hayden Stites
Requires-Python: >=3.9,<4.0
Classifier: Development Status :: 5 - Production/Stable
Classifier: Environment :: GPU :: NVIDIA CUDA
Classifier: Framework :: napari
Classifier: Intended Audience :: Science/Research
Classifier: License :: OSI Approved :: MIT License
Classifier: Operating System :: OS Independent
Classifier: Programming Language :: Python :: 3
Classifier: Programming Language :: Python :: 3.9
Classifier: Programming Language :: Python :: 3.10
Classifier: Programming Language :: Python :: 3.11
Classifier: Programming Language :: Python :: 3.12
Classifier: Programming Language :: Python :: 3.13
Classifier: Topic :: Documentation :: Sphinx
Classifier: Topic :: Scientific/Engineering :: Artificial Intelligence
Classifier: Topic :: Scientific/Engineering :: Image Processing
Provides-Extra: napari
Requires-Dist: czifile (>=2019.7.2,<2020.0.0)
Requires-Dist: magicgui (>=0.6.0,<=0.8.2)
Requires-Dist: napari (>=0.4.13,<0.5.0) ; extra == "napari"
Requires-Dist: numpy (>=1.22.4,<2.0.0)
Requires-Dist: pillow (>=9.1.0)
Requires-Dist: psutil (>=5.0.0)
Requires-Dist: pytorch-msssim (>=1.0.0,<2.0.0)
Requires-Dist: scikit-image (>=0.18.0)
Requires-Dist: scikit-optimize (>=0.9.0)
Requires-Dist: tifffile (>=2019.7.26)
Requires-Dist: timm (>=0.8.0)
Requires-Dist: torch (>=1.11.0)
Requires-Dist: tqdm (>=4.0.0,<5.0.0)
Project-URL: Documentation, https://ucsdmanorlab.github.io/PSSR2
Project-URL: Repository, https://github.com/ucsdmanorlab/PSSR2
